{
  "db_name": "PostgreSQL",
  "query": "SELECT resource as \"resource: FHIRJson<Resource>\" FROM resources WHERE tenant = $1 AND project = $2 AND id = $3 ORDER BY sequence DESC",
  "describe": {
    "columns": [
      {
        "ordinal": 0,
        "name": "resource: FHIRJson<Resource>",
        "type_info": "Jsonb"
      }
    ],
    "parameters": {
      "Left": [
        "Text",
        "Text",
        "Text"
      ]
    },
    "nullable": [
      false
    ]
  },
  "hash": "3011c123551d1d9ac6593b690a9cbc1082a52c4e47624387f23b18fa89e48256"
}
