{
  "db_name": "PostgreSQL",
  "query": "DELETE FROM projects WHERE id = $1 RETURNING id, tenant, fhir_version as \"fhir_version: SupportedFHIRVersions\"",
  "describe": {
    "columns": [
      {
        "ordinal": 0,
        "name": "id",
        "type_info": "Text"
      },
      {
        "ordinal": 1,
        "name": "tenant",
        "type_info": "Text"
      },
      {
        "ordinal": 2,
        "name": "fhir_version: SupportedFHIRVersions",
        "type_info": {
          "Custom": {
            "name": "fhir_version",
            "kind": {
              "Enum": [
                "r4",
                "r4b",
                "r5"
              ]
            }
          }
        }
      }
    ],
    "parameters": {
      "Left": [
        "Text"
      ]
    },
    "nullable": [
      false,
      false,
      false
    ]
  },
  "hash": "bc0f159b6e65cc96e605b9b304e9a12cdb7e173cf75c3eb1c0637a91ee371573"
}
